zink/__init__.py
zink/extractor.py
zink/merger.py
zink/passage_processors.py
zink/pipeline.py
zink/result.py
zink/server.py
zink/zink.py
zink/data/__init__.py
zink/data/replacements.json.gzip
zink/misc/create_automaton.py
zink/misc/fast_search.py
zink/replacer/__init__.py
zink/replacer/base.py
zink/replacer/fixed.py
zink/replacer/json_mapping.py
zink/replacer/rdate.py
zink/replacer/rdefault.py
zink/replacer/replacer.py
zink/replacer/rfakerjson.py
zink/replacer/rperson.py
zink/replacer/vars.py
zink/tests/__init__.py
zink/tests/test_basic.py
zink/tests/test_exclusion.py
zink/tests/test_persistent_mapping.py
zink/tests/test_shield.py
zink/tests/test_thread.py
zink/tests/test_thread2.py
zink/tests/data/sample.txt
zink/utils/__init__.py
zink/utils/data_utils.py
zink/utils/paths.py
zink-0.7.0.dist-info/METADATA
zink-0.7.0.dist-info/WHEEL
zink-0.7.0.dist-info/licenses/LICENSE
zink-0.7.0.dist-info/RECORD
