Metadata-Version: 2.4
Name: zink
Version: 0.7.0
Summary: Zink lets you safeguard privacy by detecting sensitive information and replacing it with secure, customizable placeholders.
Project-URL: Homepage, https://github.com/deepanwadhwa/zink
Project-URL: Repository, https://github.com/deepanwadhwa/zink
Project-URL: Documentation, https://zink.readthedocs.io/en/latest/
Author: Deepan Wadhwa
License-File: LICENSE
Requires-Python: >=3.11
Requires-Dist: faker>=37.0.0
Requires-Dist: nltk>=3.9.1
Provides-Extra: cpu
Requires-Dist: gliner>=0.2.17; extra == 'cpu'
Requires-Dist: onnxruntime>=1.17.0; extra == 'cpu'
Provides-Extra: gpu
Requires-Dist: gliner>=0.2.17; extra == 'gpu'
Requires-Dist: onnxruntime-gpu>=1.17.0; extra == 'gpu'
